Tarea3/__init__.py
Tarea3/principal.py
Tarea3/controladores/mostrar_reservas.py
Tarea3/controladores/mysql.py
Tarea3/controladores/reservar.py
Tarea3/controladores/__pycache__/mostrar_reservas.cpython-312.pyc
Tarea3/controladores/__pycache__/mysql.cpython-312.pyc
Tarea3/controladores/__pycache__/reservar.cpython-312.pyc
Tarea3/imagenes/brianda.png
Tarea3/imagenes/icon.png
Tarea3/imagenes/imagenes.qrc
Tarea3/imagenes/imagenes_rc.py
Tarea3/imagenes/refresh.png
Tarea3/imagenes/reserva.png
Tarea3/imagenes/volver.png
Tarea3/imagenes/__pycache__/imagenes_rc.cpython-312.pyc
Tarea3/modelo/reservas.sql
Tarea3/ui/mostrar_reservas.ui
Tarea3/ui/reservar.ui
Tarea3/vistas/vmostrar_reservas.py
Tarea3/vistas/vreservar.py
Tarea3/vistas/__pycache__/mostrar_reservas.cpython-312.pyc
Tarea3/vistas/__pycache__/vmostrar_reservas.cpython-312.pyc
Tarea3/vistas/__pycache__/vreservar.cpython-312.pyc
hotel_brianda_jta-0.1.dist-info/METADATA
hotel_brianda_jta-0.1.dist-info/WHEEL
hotel_brianda_jta-0.1.dist-info/top_level.txt
hotel_brianda_jta-0.1.dist-info/RECORD
